prettify_json/__init__.py
prettify_json-0.1.1.dist-info/LICENSE.txt
prettify_json-0.1.1.dist-info/METADATA
prettify_json-0.1.1.dist-info/WHEEL
prettify_json-0.1.1.dist-info/top_level.txt
prettify_json-0.1.1.dist-info/RECORD
