Metadata-Version: 2.1
Name: prettify-json
Version: 0.1.1
Summary: make pretty json
Author-email: jinjin xu <jinxu95@outlook.com>
Project-URL: Homepage, https://github.com/VeritasXu/prettify-json
Project-URL: Issues, https://github.com/VeritasXu/prettify-json/issues
Classifier: Programming Language :: Python :: 3
Classifier: License :: OSI Approved :: MIT License
Classifier: Operating System :: OS Independent
Requires-Python: >=3.6
License-File: LICENSE.txt
